discontrol
