Metadata-Version: 2.1
Name: discontrol
Version: 0.6
Summary: Module for control discord accounts. DONT SUPORTS BOTS!
Home-page: UNKNOWN
Author-email: isgamekillerept@gmail.com
License: UNKNOWN
Platform: UNKNOWN
